loveslide/__init__.py
loveslide/knockoffs.py
loveslide/love.py
loveslide/plotting.py
loveslide/score.py
loveslide/slide.py
loveslide/tools.py
loveslide-0.0.5.dist-info/METADATA
loveslide-0.0.5.dist-info/WHEEL
loveslide-0.0.5.dist-info/top_level.txt
loveslide-0.0.5.dist-info/RECORD
